ass3/boothsMultiplier/booth.v
module booth (
    input wire clk, 
    input wire rst, 
    input [7:0] x, 
    input [7:0] y, 
    output reg [15:0] s
);

    reg signed [16:0] addend = 0;
    reg signed [16:0] subtra = 0;
    reg signed [16:0] product = 0;

    reg [8:0] state = 0;

    wire signed [15:0] pwire;

    assign pwire = product >>> 1;

    integer i;

    always @ (posedge clk) begin
        if (rst) begin
            state <= 0;
        end
        else if (state == 0) begin
            addend <= { x[7:0], 9'b0 };
            subtra <= {-x[7:0], 9'b0 };
            product <= { 8'b0, y[7:0], 1'b0 };

            state <= state + 1;
        end
        else if (state == 9) begin
            s <= pwire;
            state <= 0;
        end

        for(i = 1; i < 9; i = i + 1) begin
            if (state == i && ~rst) begin
                case(product[1:0])
                    2'b01: product <= (product + addend) >>> 1;
                    2'b10: product <= (product + subtra) >>> 1;
                    default: product <= product >>> 1;
                endcase
                state <= state + 1;
            end
        end
    end

endmodule

ass3/boothsMultiplier/TBbooth.v
module TBbooth;
    
    reg signed [7:0] a;
    reg signed [7:0] b;
    reg clk = 0;
    reg rst = 1;

    always #1 clk = !clk;

    wire signed [15:0] out;

    booth DUT (
        .clk(clk),
        .rst(rst),
        .x(a),
        .y(b),
        .s(out)
    );

    initial begin
        $dumpfile("booth.vcd");
        $dumpvars;

        #2;
        rst = 0;

        // Test for corner cases
        a =  3; b = -8; #20;
        $display("a = %d, b = %d, a*b = %d", a, b, out);

        a = 10; b = -8; #20;
        $display("a = %d, b = %d, a*b = %d", a, b, out);

        a = -1; b = -1; #20;
        $display("a = %d, b = %d, a*b = %d", a, b, out);

        a = 127; b = 127; #20;
        $display("a = %d, b = %d, a*b = %d", a, b, out);

        a = 127; b = -128; #100;
        $display("a = %d, b = %d, a*b = %d", a, b, out);

        $finish;
    end

endmodule // TBbooth

ass3/boothsMultiplier/booth.vcd
$date
	Tue May  7 21:36:22 2024
$end
$version
	Icarus Verilog
$end
$timescale
	1s
$end
$scope module TBbooth $end
$var wire 16 ! out [15:0] $end
$var reg 8 " a [7:0] $end
$var reg 8 # b [7:0] $end
$var reg 1 $ clk $end
$var reg 1 % rst $end
$scope module DUT $end
$var wire 1 $ clk $end
$var wire 1 % rst $end
$var wire 8 & x [7:0] $end
$var wire 8 ' y [7:0] $end
$var wire 16 ( pwire [15:0] $end
$var reg 17 ) addend [16:0] $end
$var reg 17 * product [16:0] $end
$var reg 16 + s [15:0] $end
$var reg 9 , state [8:0] $end
$var reg 17 - subtra [16:0] $end
$var integer 32 . i [31:0] $end
$upscope $end
$upscope $end
$enddefinitions $end
#0
$dumpvars
bx .
b0 -
b0 ,
bx +
b0 *
b0 )
b0 (
bx '
bx &
1%
0$
bx #
bx "
bx !
$end
#1
b1001 .
1$
#2
0$
b11111000 #
b11111000 '
b11 "
b11 &
0%
#3
b11111000 (
b1 ,
b111110000 *
b11111101000000000 -
b11000000000 )
b1001 .
1$
#4
0$
#5
b1111100 (
b10 ,
b11111000 *
b1001 .
1$
#6
0$
#7
b111110 (
b11 ,
b1111100 *
b1001 .
1$
#8
0$
#9
b11111 (
b100 ,
b111110 *
b1001 .
1$
#10
0$
#11
b1111111010001111 (
b101 ,
b11111110100011111 *
b1001 .
1$
#12
0$
#13
b1111111101000111 (
b110 ,
b11111111010001111 *
b1001 .
1$
#14
0$
#15
b1111111110100011 (
b111 ,
b11111111101000111 *
b1001 .
1$
#16
0$
#17
b1111111111010001 (
b1000 ,
b11111111110100011 *
b1001 .
1$
#18
0$
#19
b1111111111101000 (
b1001 ,
b11111111111010001 *
b1001 .
1$
#20
0$
#21
b0 ,
b1111111111101000 !
b1111111111101000 +
b1001 .
1$
#22
0$
b1010 "
b1010 &
#23
b11111000 (
b1 ,
b111110000 *
b11110110000000000 -
b1010000000000 )
b1001 .
1$
#24
0$
#25
b1111100 (
b10 ,
b11111000 *
b1001 .
1$
#26
0$
#27
b111110 (
b11 ,
b1111100 *
b1001 .
1$
#28
0$
#29
b11111 (
b100 ,
b111110 *
b1001 .
1$
#30
0$
#31
b1111101100001111 (
b101 ,
b11111011000011111 *
b1001 .
1$
#32
0$
#33
b1111110110000111 (
b110 ,
b11111101100001111 *
b1001 .
1$
#34
0$
#35
b1111111011000011 (
b111 ,
b11111110110000111 *
b1001 .
1$
#36
0$
#37
b1111111101100001 (
b1000 ,
b11111111011000011 *
b1001 .
1$
#38
0$
#39
b1111111110110000 (
b1001 ,
b11111111101100001 *
b1001 .
1$
#40
0$
#41
b0 ,
b1111111110110000 !
b1111111110110000 +
b1001 .
1$
#42
0$
b11111111 #
b11111111 '
b11111111 "
b11111111 &
#43
b11111111 (
b1 ,
b111111110 *
b1000000000 -
b11111111000000000 )
b1001 .
1$
#44
0$
#45
b10 ,
b111111111 *
b1001 .
1$
#46
0$
#47
b1111111 (
b11 ,
b11111111 *
b1001 .
1$
#48
0$
#49
b111111 (
b100 ,
b1111111 *
b1001 .
1$
#50
0$
#51
b11111 (
b101 ,
b111111 *
b1001 .
1$
#52
0$
#53
b1111 (
b110 ,
b11111 *
b1001 .
1$
#54
0$
#55
b111 (
b111 ,
b1111 *
b1001 .
1$
#56
0$
#57
b11 (
b1000 ,
b111 *
b1001 .
1$
#58
0$
#59
b1 (
b1001 ,
b11 *
b1001 .
1$
#60
0$
#61
b0 ,
b1 !
b1 +
b1001 .
1$
#62
0$
b1111111 #
b1111111 '
b1111111 "
b1111111 &
#63
b1111111 (
b1 ,
b11111110 *
b10000001000000000 -
b1111111000000000 )
b1001 .
1$
#64
0$
#65
b1100000010111111 (
b10 ,
b11000000101111111 *
b1001 .
1$
#66
0$
#67
b1110000001011111 (
b11 ,
b11100000010111111 *
b1001 .
1$
#68
0$
#69
b1111000000101111 (
b100 ,
b11110000001011111 *
b1001 .
1$
#70
0$
#71
b1111100000010111 (
b101 ,
b11111000000101111 *
b1001 .
1$
#72
0$
#73
b1111110000001011 (
b110 ,
b11111100000010111 *
b1001 .
1$
#74
0$
#75
b1111111000000101 (
b111 ,
b11111110000001011 *
b1001 .
1$
#76
0$
#77
b1111111100000010 (
b1000 ,
b11111111000000101 *
b1001 .
1$
#78
0$
#79
b11111100000001 (
b1001 ,
b111111000000010 *
b1001 .
1$
#80
0$
#81
b0 ,
b11111100000001 !
b11111100000001 +
b1001 .
1$
#82
0$
b10000000 #
b10000000 '
#83
b10000000 (
b1 ,
b100000000 *
b1001 .
1$
#84
0$
#85
b1000000 (
b10 ,
b10000000 *
b1001 .
1$
#86
0$
#87
b100000 (
b11 ,
b1000000 *
b1001 .
1$
#88
0$
#89
b10000 (
b100 ,
b100000 *
b1001 .
1$
#90
0$
#91
b1000 (
b101 ,
b10000 *
b1001 .
1$
#92
0$
#93
b100 (
b110 ,
b1000 *
b1001 .
1$
#94
0$
#95
b10 (
b111 ,
b100 *
b1001 .
1$
#96
0$
#97
b1 (
b1000 ,
b10 *
b1001 .
1$
#98
0$
#99
b1100000010000000 (
b1001 ,
b11000000100000001 *
b1001 .
1$
#100
0$
#101
b0 ,
b1100000010000000 !
b1100000010000000 +
b1001 .
1$
#102
0$
#103
b10000000 (
b1 ,
b100000000 *
b1001 .
1$
#104
0$
#105
b1000000 (
b10 ,
b10000000 *
b1001 .
1$
#106
0$
#107
b100000 (
b11 ,
b1000000 *
b1001 .
1$
#108
0$
#109
b10000 (
b100 ,
b100000 *
b1001 .
1$
#110
0$
#111
b1000 (
b101 ,
b10000 *
b1001 .
1$
#112
0$
#113
b100 (
b110 ,
b1000 *
b1001 .
1$
#114
0$
#115
b10 (
b111 ,
b100 *
b1001 .
1$
#116
0$
#117
b1 (
b1000 ,
b10 *
b1001 .
1$
#118
0$
#119
b1100000010000000 (
b1001 ,
b11000000100000001 *
b1001 .
1$
#120
0$
#121
b0 ,
b1001 .
1$
#122
0$
#123
b10000000 (
b1 ,
b100000000 *
b1001 .
1$
#124
0$
#125
b1000000 (
b10 ,
b10000000 *
b1001 .
1$
#126
0$
#127
b100000 (
b11 ,
b1000000 *
b1001 .
1$
#128
0$
#129
b10000 (
b100 ,
b100000 *
b1001 .
1$
#130
0$
#131
b1000 (
b101 ,
b10000 *
b1001 .
1$
#132
0$
#133
b100 (
b110 ,
b1000 *
b1001 .
1$
#134
0$
#135
b10 (
b111 ,
b100 *
b1001 .
1$
#136
0$
#137
b1 (
b1000 ,
b10 *
b1001 .
1$
#138
0$
#139
b1100000010000000 (
b1001 ,
b11000000100000001 *
b1001 .
1$
#140
0$
#141
b0 ,
b1001 .
1$
#142
0$
#143
b10000000 (
b1 ,
b100000000 *
b1001 .
1$
#144
0$
#145
b1000000 (
b10 ,
b10000000 *
b1001 .
1$
#146
0$
#147
b100000 (
b11 ,
b1000000 *
b1001 .
1$
#148
0$
#149
b10000 (
b100 ,
b100000 *
b1001 .
1$
#150
0$
#151
b1000 (
b101 ,
b10000 *
b1001 .
1$
#152
0$
#153
b100 (
b110 ,
b1000 *
b1001 .
1$
#154
0$
#155
b10 (
b111 ,
b100 *
b1001 .
1$
#156
0$
#157
b1 (
b1000 ,
b10 *
b1001 .
1$
#158
0$
#159
b1100000010000000 (
b1001 ,
b11000000100000001 *
b1001 .
1$
#160
0$
#161
b0 ,
b1001 .
1$
#162
0$
#163
b10000000 (
b1 ,
b100000000 *
b1001 .
1$
#164
0$
#165
b1000000 (
b10 ,
b10000000 *
b1001 .
1$
#166
0$
#167
b100000 (
b11 ,
b1000000 *
b1001 .
1$
#168
0$
#169
b10000 (
b100 ,
b100000 *
b1001 .
1$
#170
0$
#171
b1000 (
b101 ,
b10000 *
b1001 .
1$
#172
0$
#173
b100 (
b110 ,
b1000 *
b1001 .
1$
#174
0$
#175
b10 (
b111 ,
b100 *
b1001 .
1$
#176
0$
#177
b1 (
b1000 ,
b10 *
b1001 .
1$
#178
0$
#179
b1100000010000000 (
b1001 ,
b11000000100000001 *
b1001 .
1$
#180
0$
#181
b0 ,
b1001 .
1$
