ass1/operation/twoclock.v
module array_sum(
    input [79:0] num1,
    input [79:0] num2,
    output reg [15:0] sum,
    input clk,
    input res
);

integer i;
reg [15:0] products [9:0]; // Array to store products
reg [15:0] temp_sum;       // Intermediate sum register

always @(res == 1)
begin
sum <=0;
temp_sum <=0;
end


always @(negedge clk) begin
        for (i = 0; i < 10; i = i + 1) begin
            products[i] <= num1[i*8 +: 8] * num2[i*8 +: 8]; // Store products in array
        end
end

always @(negedge clk) begin
    sum <= temp_sum; // Assign temporary sum to the output sum on posedge of clock
    temp_sum <= products[0] + products[1] + products[2] + products[3] + products[4] + 
                products[5] + products[6] + products[7] + products[8] + products[9]; // Sum products on posedge of clock
end

endmodule

ass1/operation/TBoneclock.v
`timescale 1ns / 1ps

module tb_array_sum;

// Inputs and outputs
reg [79:0] num1; // Packed array to hold 10 8-bit numbers
reg [79:0] num2; // Packed array to hold 10 8-bit numbers
wire [15:0] sum; // Output sum
reg res;

// Clock signal
reg clk = 0; // Clock signal
always #25 clk = ~clk; // Toggle clock every 5 time units

// Internal variables
integer i; // Integer variable for loop indexing

// Instantiate the array_sum module
array_sum sum_module(
    .num1(num1),
    .num2(num2),
    .sum(sum),
    .clk(clk),
    .res(res)
    
);

// Initial block for testbench
initial begin
    // Open VCD file for dumping waveform
    $dumpfile("oneclock.vcd");
    $dumpvars(0, tb_array_sum);

    // First test case
    num1 = {8'b00000010, 8'b00000100, 8'b00000110, 8'b00001000, 8'b00001010, 8'b00001100, 8'b00001110, 8'b00010000, 8'b00010010, 8'b00010100};
    num2 = {8'b00000001, 8'b00000011, 8'b00000101, 8'b00000111, 8'b00001001, 8'b00001011, 8'b00001101, 8'b00001111, 8'b00010001, 8'b00010011};
    res=1;
    #1
    res=0;
    #99
    // Second test case
    num1 = {8'b00000101, 8'b00000100, 8'b00000011, 8'b00000010, 8'b00000001, 8'b00000001, 8'b00000010, 8'b00000011, 8'b00000100, 8'b00000101};
    num2 = {8'b00000001, 8'b00000010, 8'b00000011, 8'b00000100, 8'b00000101, 8'b00000110, 8'b00000111, 8'b00001000, 8'b00001001, 8'b00001010};
    
    #100
    $finish;
end

endmodule

ass1/operation/twoclock.vcd
$date
	Tue Apr  2 10:39:16 2024
$end
$version
	Icarus Verilog
$end
$timescale
	1ps
$end
$scope module tb_array_sum $end
$var wire 16 ! sum [15:0] $end
$var reg 1 " clk $end
$var reg 80 # num1 [79:0] $end
$var reg 80 $ num2 [79:0] $end
$var reg 1 % res $end
$scope module sum_module $end
$var wire 1 " clk $end
$var wire 80 & num1 [79:0] $end
$var wire 80 ' num2 [79:0] $end
$var wire 1 % res $end
$var reg 16 ( sum [15:0] $end
$var reg 16 ) temp_sum [15:0] $end
$var integer 32 * i [31:0] $end
$upscope $end
$upscope $end
$enddefinitions $end
#0
$dumpvars
b1010 *
b0 )
b0 (
b1000000110000010100000111000010010000101100001101000011110001000100010011 '
b10000001000000011000001000000010100000110000001110000100000001001000010100 &
1%
b1000000110000010100000111000010010000101100001101000011110001000100010011 $
b10000001000000011000001000000010100000110000001110000100000001001000010100 #
0"
b0 !
$end
#1000
0%
#25000
1"
#50000
b10110010110 )
b1010 *
0"
#75000
1"
#100000
b10110010110 !
b10110010110 (
b1010 *
0"
#125000
1"
#131000
b1000000100000001100000100000001010000011000000111000010000000100100001010 $
b1000000100000001100000100000001010000011000000111000010000000100100001010 '
b101000001000000001100000010000000010000000100000010000000110000010000000101 #
b101000001000000001100000010000000010000000100000010000000110000010000000101 &
#150000
b1010 *
0"
#175000
1"
#200000
b10100101 )
b1010 *
0"
#225000
1"
#250000
b10100101 !
b10100101 (
b1010 *
0"
#275000
1"
#300000
b1010 *
0"
#325000
1"
#350000
b1010 *
0"
#375000
1"
#400000
b1010 *
0"
