ass2/unishiftRegister/unishift.v
module universalShift(
  input clk, 
  input rst_n, 
  input [8:0] select, // select operation
  input [15:0] p_din,  // parallel data in 
  input s_left_din,   // serial left data in
  input s_right_din,  // serial right data in
  output reg [15:0] p_dout, //parallel data out
  output reg s_left_dout, // serial left data out
  output reg s_right_dout // serial right data out
);

reg pdoutbuffer;

always @ (posedge clk) begin : select_magic
if(rst_n) begin : reset_logic
    p_dout = 16'b0;
    s_left_dout = 1'b0;     
    s_right_dout = 1'b0; 
end
else begin
 case(select) 
        9'b000000001: begin // SISO left shift
        s_left_dout = p_dout[15];
        p_dout = p_dout << 1;
        p_dout = {p_dout[15:1], s_right_din};
                    end
        9'b000000010: begin // SISO right shift
        s_right_dout = p_dout[0];
        p_dout = p_dout >> 1;
        p_dout = {s_left_din, p_dout[14:0]};
                      end
        9'b000000100: begin // SIPO left shift
        s_left_dout = p_dout[15];
        p_dout = p_dout << 1;
        p_dout = {p_dout[15:1], s_right_din};
                      end
        9'b000001000: begin // SIPO right shift
        s_right_dout = p_dout[0];
        p_dout = p_dout >> 1;
        p_dout = {s_left_din, p_dout[14:0]};
                      end
        9'b000010000: begin // PIPO left shift
        p_dout = p_din;
        p_dout = p_dout << 1;
                      end
        9'b000100000: begin // PIPO right shift
        p_dout = p_din;
        p_dout = p_dout >> 1;
                      end
        9'b001000000: begin // PISO left shift
        p_dout = p_din;
        s_left_dout = p_dout[15];
        p_dout = p_dout << 1;
                      end
        9'b010000000: begin // PISO right shift
        p_dout = p_din;
        s_right_dout = p_dout[0];
        p_dout = p_dout >> 1;    
                      end
        9'b100000000: begin // Do nothing
                      p_dout = p_dout;
                      end
        default: begin
          p_dout = 16'b0;
          s_left_dout =0;
          s_right_dout =0;
        end // Do nothing
      endcase
end
end
endmodule

ass2/unishiftRegister/TBunishift.v
`timescale 1ns / 1ps

module universal_shift_reg_tb;

  // Parameters
  parameter CLK_PERIOD = 10; // Clock period in ns

  // Signals
  reg clk;
  reg rst_n;
  reg [8:0] select;
  reg [15:0] p_din;
  reg s_left_din;
  reg s_right_din;
  wire [15:0] p_dout;
  wire s_left_dout;
  wire s_right_dout;

  // Instantiate the universal_shift_reg module
  universalShift uut (
    .clk(clk),
    .rst_n(rst_n),
    .select(select),
    .p_din(p_din),
    .s_left_din(s_left_din),
    .s_right_din(s_right_din),
    .p_dout(p_dout),
    .s_left_dout(s_left_dout),
    .s_right_dout(s_right_dout)
  );

  // Clock generation
  always #((CLK_PERIOD / 2)) clk <= ~clk;

  // Test stimulus
  initial begin
    $dumpfile("unishift.vcd");
    $dumpvars(0, universal_shift_reg_tb);
    
    // Initialize inputs
    clk = 0;
    rst_n = 1;
    select = 9'b100000000;
    p_din = 0;
    s_left_din = 0;
    s_right_din = 0;

    #11
    rst_n = 0;
    #19
    select = 9'b000000001; // SISO left shift
    s_right_din = 1;
    #160
    s_right_din = 0;
    #200

    select = 9'b000000010; // SISO right shift
    s_left_din = 0;
    #160
    s_left_din = 1;
    #200

    select = 9'b000000100; // SIPO left shift
    s_right_din = 1;
    #160
    s_right_din = 0;
    #200

    select = 9'b000001000; // SIPO right shift
    s_left_din = 0;
    #160
    s_left_din = 1;
    #200

    select = 9'b000010000; // PIPO left shift
    p_din = 16'b1010101010101010;
    #200

    select = 9'b000100000; // PIPO right shift
    p_din = 16'b1110111010101010;
    #200

    select = 9'b001000000; // PISO left shift
    p_din = 16'b1110110010101110;
    #200

    select = 9'b010000000; // PISO right shift
    p_din = 16'b1110110010101110;
    #200

    select = 9'b100000000; // Do nothing
    p_din = 16'b1110110010101110;
    #200
    // End of simulation
    $finish;
  end

endmodule

ass2/unishiftRegister/unishift.vcd
$date
	Tue May  7 16:55:36 2024
$end
$version
	Icarus Verilog
$end
$timescale
	1ps
$end
$scope module universal_shift_reg_tb $end
$var wire 1 ! s_right_dout $end
$var wire 1 " s_left_dout $end
$var wire 16 # p_dout [15:0] $end
$var reg 1 $ clk $end
$var reg 16 % p_din [15:0] $end
$var reg 1 & rst_n $end
$var reg 1 ' s_left_din $end
$var reg 1 ( s_right_din $end
$var reg 9 ) select [8:0] $end
$scope module uut $end
$var wire 1 $ clk $end
$var wire 16 * p_din [15:0] $end
$var wire 1 & rst_n $end
$var wire 1 ' s_left_din $end
$var wire 1 ( s_right_din $end
$var wire 9 + select [8:0] $end
$var reg 16 , p_dout [15:0] $end
$var reg 1 " s_left_dout $end
$var reg 1 ! s_right_dout $end
$scope begin select_magic $end
$scope begin reset_logic $end
$upscope $end
$upscope $end
$upscope $end
$upscope $end
$enddefinitions $end
#0
$dumpvars
bx ,
b100000000 +
b0 *
b100000000 )
0(
0'
1&
b0 %
0$
bx #
x"
x!
$end
#5000
0!
0"
b0 #
b0 ,
1$
#10000
0$
#11000
0&
#15000
1$
#20000
0$
#25000
1$
#30000
0$
1(
b1 )
b1 +
#35000
b1 #
b1 ,
1$
#40000
0$
#45000
b11 #
b11 ,
1$
#50000
0$
#55000
b111 #
b111 ,
1$
#60000
0$
#65000
b1111 #
b1111 ,
1$
#70000
0$
#75000
b11111 #
b11111 ,
1$
#80000
0$
#85000
b111111 #
b111111 ,
1$
#90000
0$
#95000
b1111111 #
b1111111 ,
1$
#100000
0$
#105000
b11111111 #
b11111111 ,
1$
#110000
0$
#115000
b111111111 #
b111111111 ,
1$
#120000
0$
#125000
b1111111111 #
b1111111111 ,
1$
#130000
0$
#135000
b11111111111 #
b11111111111 ,
1$
#140000
0$
#145000
b111111111111 #
b111111111111 ,
1$
#150000
0$
#155000
b1111111111111 #
b1111111111111 ,
1$
#160000
0$
#165000
b11111111111111 #
b11111111111111 ,
1$
#170000
0$
#175000
b111111111111111 #
b111111111111111 ,
1$
#180000
0$
#185000
b1111111111111111 #
b1111111111111111 ,
1$
#190000
0$
0(
#195000
b1111111111111110 #
b1111111111111110 ,
1"
1$
#200000
0$
#205000
b1111111111111100 #
b1111111111111100 ,
1$
#210000
0$
#215000
b1111111111111000 #
b1111111111111000 ,
1$
#220000
0$
#225000
b1111111111110000 #
b1111111111110000 ,
1$
#230000
0$
#235000
b1111111111100000 #
b1111111111100000 ,
1$
#240000
0$
#245000
b1111111111000000 #
b1111111111000000 ,
1$
#250000
0$
#255000
b1111111110000000 #
b1111111110000000 ,
1$
#260000
0$
#265000
b1111111100000000 #
b1111111100000000 ,
1$
#270000
0$
#275000
b1111111000000000 #
b1111111000000000 ,
1$
#280000
0$
#285000
b1111110000000000 #
b1111110000000000 ,
1$
#290000
0$
#295000
b1111100000000000 #
b1111100000000000 ,
1$
#300000
0$
#305000
b1111000000000000 #
b1111000000000000 ,
1$
#310000
0$
#315000
b1110000000000000 #
b1110000000000000 ,
1$
#320000
0$
#325000
b1100000000000000 #
b1100000000000000 ,
1$
#330000
0$
#335000
b1000000000000000 #
b1000000000000000 ,
1$
#340000
0$
#345000
b0 #
b0 ,
1$
#350000
0$
#355000
0"
1$
#360000
0$
#365000
1$
#370000
0$
#375000
1$
#380000
0$
#385000
1$
#390000
0$
b10 )
b10 +
#395000
1$
#400000
0$
#405000
1$
#410000
0$
#415000
1$
#420000
0$
#425000
1$
#430000
0$
#435000
1$
#440000
0$
#445000
1$
#450000
0$
#455000
1$
#460000
0$
#465000
1$
#470000
0$
#475000
1$
#480000
0$
#485000
1$
#490000
0$
#495000
1$
#500000
0$
#505000
1$
#510000
0$
#515000
1$
#520000
0$
#525000
1$
#530000
0$
#535000
1$
#540000
0$
#545000
1$
#550000
0$
1'
#555000
b1000000000000000 #
b1000000000000000 ,
1$
#560000
0$
#565000
b1100000000000000 #
b1100000000000000 ,
1$
#570000
0$
#575000
b1110000000000000 #
b1110000000000000 ,
1$
#580000
0$
#585000
b1111000000000000 #
b1111000000000000 ,
1$
#590000
0$
#595000
b1111100000000000 #
b1111100000000000 ,
1$
#600000
0$
#605000
b1111110000000000 #
b1111110000000000 ,
1$
#610000
0$
#615000
b1111111000000000 #
b1111111000000000 ,
1$
#620000
0$
#625000
b1111111100000000 #
b1111111100000000 ,
1$
#630000
0$
#635000
b1111111110000000 #
b1111111110000000 ,
1$
#640000
0$
#645000
b1111111111000000 #
b1111111111000000 ,
1$
#650000
0$
#655000
b1111111111100000 #
b1111111111100000 ,
1$
#660000
0$
#665000
b1111111111110000 #
b1111111111110000 ,
1$
#670000
0$
#675000
b1111111111111000 #
b1111111111111000 ,
1$
#680000
0$
#685000
b1111111111111100 #
b1111111111111100 ,
1$
#690000
0$
#695000
b1111111111111110 #
b1111111111111110 ,
1$
#700000
0$
#705000
b1111111111111111 #
b1111111111111111 ,
1$
#710000
0$
#715000
b1111111111111111 #
b1111111111111111 ,
1!
1$
#720000
0$
#725000
b1111111111111111 #
b1111111111111111 ,
1$
#730000
0$
#735000
b1111111111111111 #
b1111111111111111 ,
1$
#740000
0$
#745000
b1111111111111111 #
b1111111111111111 ,
1$
#750000
0$
1(
b100 )
b100 +
#755000
b1111111111111111 #
b1111111111111111 ,
1"
1$
#760000
0$
#765000
b1111111111111111 #
b1111111111111111 ,
1$
#770000
0$
#775000
b1111111111111111 #
b1111111111111111 ,
1$
#780000
0$
#785000
b1111111111111111 #
b1111111111111111 ,
1$
#790000
0$
#795000
b1111111111111111 #
b1111111111111111 ,
1$
#800000
0$
#805000
b1111111111111111 #
b1111111111111111 ,
1$
#810000
0$
#815000
b1111111111111111 #
b1111111111111111 ,
1$
#820000
0$
#825000
b1111111111111111 #
b1111111111111111 ,
1$
#830000
0$
#835000
b1111111111111111 #
b1111111111111111 ,
1$
#840000
0$
#845000
b1111111111111111 #
b1111111111111111 ,
1$
#850000
0$
#855000
b1111111111111111 #
b1111111111111111 ,
1$
#860000
0$
#865000
b1111111111111111 #
b1111111111111111 ,
1$
#870000
0$
#875000
b1111111111111111 #
b1111111111111111 ,
1$
#880000
0$
#885000
b1111111111111111 #
b1111111111111111 ,
1$
#890000
0$
#895000
b1111111111111111 #
b1111111111111111 ,
1$
#900000
0$
#905000
b1111111111111111 #
b1111111111111111 ,
1$
#910000
0$
0(
#915000
b1111111111111110 #
b1111111111111110 ,
1$
#920000
0$
#925000
b1111111111111100 #
b1111111111111100 ,
1$
#930000
0$
#935000
b1111111111111000 #
b1111111111111000 ,
1$
#940000
0$
#945000
b1111111111110000 #
b1111111111110000 ,
1$
#950000
0$
#955000
b1111111111100000 #
b1111111111100000 ,
1$
#960000
0$
#965000
b1111111111000000 #
b1111111111000000 ,
1$
#970000
0$
#975000
b1111111110000000 #
b1111111110000000 ,
1$
#980000
0$
#985000
b1111111100000000 #
b1111111100000000 ,
1$
#990000
0$
#995000
b1111111000000000 #
b1111111000000000 ,
1$
#1000000
0$
#1005000
b1111110000000000 #
b1111110000000000 ,
1$
#1010000
0$
#1015000
b1111100000000000 #
b1111100000000000 ,
1$
#1020000
0$
#1025000
b1111000000000000 #
b1111000000000000 ,
1$
#1030000
0$
#1035000
b1110000000000000 #
b1110000000000000 ,
1$
#1040000
0$
#1045000
b1100000000000000 #
b1100000000000000 ,
1$
#1050000
0$
#1055000
b1000000000000000 #
b1000000000000000 ,
1$
#1060000
0$
#1065000
b0 #
b0 ,
1$
#1070000
0$
#1075000
0"
1$
#1080000
0$
#1085000
1$
#1090000
0$
#1095000
1$
#1100000
0$
#1105000
1$
#1110000
0$
0'
b1000 )
b1000 +
#1115000
0!
1$
#1120000
0$
#1125000
1$
#1130000
0$
#1135000
1$
#1140000
0$
#1145000
1$
#1150000
0$
#1155000
1$
#1160000
0$
#1165000
1$
#1170000
0$
#1175000
1$
#1180000
0$
#1185000
1$
#1190000
0$
#1195000
1$
#1200000
0$
#1205000
1$
#1210000
0$
#1215000
1$
#1220000
0$
#1225000
1$
#1230000
0$
#1235000
1$
#1240000
0$
#1245000
1$
#1250000
0$
#1255000
1$
#1260000
0$
#1265000
1$
#1270000
0$
1'
#1275000
b1000000000000000 #
b1000000000000000 ,
1$
#1280000
0$
#1285000
b1100000000000000 #
b1100000000000000 ,
1$
#1290000
0$
#1295000
b1110000000000000 #
b1110000000000000 ,
1$
#1300000
0$
#1305000
b1111000000000000 #
b1111000000000000 ,
1$
#1310000
0$
#1315000
b1111100000000000 #
b1111100000000000 ,
1$
#1320000
0$
#1325000
b1111110000000000 #
b1111110000000000 ,
1$
#1330000
0$
#1335000
b1111111000000000 #
b1111111000000000 ,
1$
#1340000
0$
#1345000
b1111111100000000 #
b1111111100000000 ,
1$
#1350000
0$
#1355000
b1111111110000000 #
b1111111110000000 ,
1$
#1360000
0$
#1365000
b1111111111000000 #
b1111111111000000 ,
1$
#1370000
0$
#1375000
b1111111111100000 #
b1111111111100000 ,
1$
#1380000
0$
#1385000
b1111111111110000 #
b1111111111110000 ,
1$
#1390000
0$
#1395000
b1111111111111000 #
b1111111111111000 ,
1$
#1400000
0$
#1405000
b1111111111111100 #
b1111111111111100 ,
1$
#1410000
0$
#1415000
b1111111111111110 #
b1111111111111110 ,
1$
#1420000
0$
#1425000
b1111111111111111 #
b1111111111111111 ,
1$
#1430000
0$
#1435000
b1111111111111111 #
b1111111111111111 ,
1!
1$
#1440000
0$
#1445000
b1111111111111111 #
b1111111111111111 ,
1$
#1450000
0$
#1455000
b1111111111111111 #
b1111111111111111 ,
1$
#1460000
0$
#1465000
b1111111111111111 #
b1111111111111111 ,
1$
#1470000
0$
b1010101010101010 %
b1010101010101010 *
b10000 )
b10000 +
#1475000
b101010101010100 #
b101010101010100 ,
1$
#1480000
0$
#1485000
b101010101010100 #
b101010101010100 ,
1$
#1490000
0$
#1495000
b101010101010100 #
b101010101010100 ,
1$
#1500000
0$
#1505000
b101010101010100 #
b101010101010100 ,
1$
#1510000
0$
#1515000
b101010101010100 #
b101010101010100 ,
1$
#1520000
0$
#1525000
b101010101010100 #
b101010101010100 ,
1$
#1530000
0$
#1535000
b101010101010100 #
b101010101010100 ,
1$
#1540000
0$
#1545000
b101010101010100 #
b101010101010100 ,
1$
#1550000
0$
#1555000
b101010101010100 #
b101010101010100 ,
1$
#1560000
0$
#1565000
b101010101010100 #
b101010101010100 ,
1$
#1570000
0$
#1575000
b101010101010100 #
b101010101010100 ,
1$
#1580000
0$
#1585000
b101010101010100 #
b101010101010100 ,
1$
#1590000
0$
#1595000
b101010101010100 #
b101010101010100 ,
1$
#1600000
0$
#1605000
b101010101010100 #
b101010101010100 ,
1$
#1610000
0$
#1615000
b101010101010100 #
b101010101010100 ,
1$
#1620000
0$
#1625000
b101010101010100 #
b101010101010100 ,
1$
#1630000
0$
#1635000
b101010101010100 #
b101010101010100 ,
1$
#1640000
0$
#1645000
b101010101010100 #
b101010101010100 ,
1$
#1650000
0$
#1655000
b101010101010100 #
b101010101010100 ,
1$
#1660000
0$
#1665000
b101010101010100 #
b101010101010100 ,
1$
#1670000
0$
b1110111010101010 %
b1110111010101010 *
b100000 )
b100000 +
#1675000
b111011101010101 #
b111011101010101 ,
1$
#1680000
0$
#1685000
b111011101010101 #
b111011101010101 ,
1$
#1690000
0$
#1695000
b111011101010101 #
b111011101010101 ,
1$
#1700000
0$
#1705000
b111011101010101 #
b111011101010101 ,
1$
#1710000
0$
#1715000
b111011101010101 #
b111011101010101 ,
1$
#1720000
0$
#1725000
b111011101010101 #
b111011101010101 ,
1$
#1730000
0$
#1735000
b111011101010101 #
b111011101010101 ,
1$
#1740000
0$
#1745000
b111011101010101 #
b111011101010101 ,
1$
#1750000
0$
#1755000
b111011101010101 #
b111011101010101 ,
1$
#1760000
0$
#1765000
b111011101010101 #
b111011101010101 ,
1$
#1770000
0$
#1775000
b111011101010101 #
b111011101010101 ,
1$
#1780000
0$
#1785000
b111011101010101 #
b111011101010101 ,
1$
#1790000
0$
#1795000
b111011101010101 #
b111011101010101 ,
1$
#1800000
0$
#1805000
b111011101010101 #
b111011101010101 ,
1$
#1810000
0$
#1815000
b111011101010101 #
b111011101010101 ,
1$
#1820000
0$
#1825000
b111011101010101 #
b111011101010101 ,
1$
#1830000
0$
#1835000
b111011101010101 #
b111011101010101 ,
1$
#1840000
0$
#1845000
b111011101010101 #
b111011101010101 ,
1$
#1850000
0$
#1855000
b111011101010101 #
b111011101010101 ,
1$
#1860000
0$
#1865000
b111011101010101 #
b111011101010101 ,
1$
#1870000
0$
b1110110010101110 %
b1110110010101110 *
b1000000 )
b1000000 +
#1875000
1"
b1101100101011100 #
b1101100101011100 ,
1$
#1880000
0$
#1885000
b1101100101011100 #
b1101100101011100 ,
1$
#1890000
0$
#1895000
b1101100101011100 #
b1101100101011100 ,
1$
#1900000
0$
#1905000
b1101100101011100 #
b1101100101011100 ,
1$
#1910000
0$
#1915000
b1101100101011100 #
b1101100101011100 ,
1$
#1920000
0$
#1925000
b1101100101011100 #
b1101100101011100 ,
1$
#1930000
0$
#1935000
b1101100101011100 #
b1101100101011100 ,
1$
#1940000
0$
#1945000
b1101100101011100 #
b1101100101011100 ,
1$
#1950000
0$
#1955000
b1101100101011100 #
b1101100101011100 ,
1$
#1960000
0$
#1965000
b1101100101011100 #
b1101100101011100 ,
1$
#1970000
0$
#1975000
b1101100101011100 #
b1101100101011100 ,
1$
#1980000
0$
#1985000
b1101100101011100 #
b1101100101011100 ,
1$
#1990000
0$
#1995000
b1101100101011100 #
b1101100101011100 ,
1$
#2000000
0$
#2005000
b1101100101011100 #
b1101100101011100 ,
1$
#2010000
0$
#2015000
b1101100101011100 #
b1101100101011100 ,
1$
#2020000
0$
#2025000
b1101100101011100 #
b1101100101011100 ,
1$
#2030000
0$
#2035000
b1101100101011100 #
b1101100101011100 ,
1$
#2040000
0$
#2045000
b1101100101011100 #
b1101100101011100 ,
1$
#2050000
0$
#2055000
b1101100101011100 #
b1101100101011100 ,
1$
#2060000
0$
#2065000
b1101100101011100 #
b1101100101011100 ,
1$
#2070000
0$
b10000000 )
b10000000 +
#2075000
0!
b111011001010111 #
b111011001010111 ,
1$
#2080000
0$
#2085000
b111011001010111 #
b111011001010111 ,
1$
#2090000
0$
#2095000
b111011001010111 #
b111011001010111 ,
1$
#2100000
0$
#2105000
b111011001010111 #
b111011001010111 ,
1$
#2110000
0$
#2115000
b111011001010111 #
b111011001010111 ,
1$
#2120000
0$
#2125000
b111011001010111 #
b111011001010111 ,
1$
#2130000
0$
#2135000
b111011001010111 #
b111011001010111 ,
1$
#2140000
0$
#2145000
b111011001010111 #
b111011001010111 ,
1$
#2150000
0$
#2155000
b111011001010111 #
b111011001010111 ,
1$
#2160000
0$
#2165000
b111011001010111 #
b111011001010111 ,
1$
#2170000
0$
#2175000
b111011001010111 #
b111011001010111 ,
1$
#2180000
0$
#2185000
b111011001010111 #
b111011001010111 ,
1$
#2190000
0$
#2195000
b111011001010111 #
b111011001010111 ,
1$
#2200000
0$
#2205000
b111011001010111 #
b111011001010111 ,
1$
#2210000
0$
#2215000
b111011001010111 #
b111011001010111 ,
1$
#2220000
0$
#2225000
b111011001010111 #
b111011001010111 ,
1$
#2230000
0$
#2235000
b111011001010111 #
b111011001010111 ,
1$
#2240000
0$
#2245000
b111011001010111 #
b111011001010111 ,
1$
#2250000
0$
#2255000
b111011001010111 #
b111011001010111 ,
1$
#2260000
0$
#2265000
b111011001010111 #
b111011001010111 ,
1$
#2270000
0$
b100000000 )
b100000000 +
