ass1/shift/shift.v
module dflip(
    input din,
    input clk,
    input res,
    output reg dout
);

always @(res == 1) begin
    dout <=0;
end

always @(negedge clk) begin
    dout = din;
end

endmodule

module shiftreg (
  input din,
  input clk,
  input res,
  output [3:0] dout
);
  genvar i;
  
  generate
    dflip fa (
        .din(din),
        .clk(clk),
        .res(res),
        .dout(dout[0])
      );
    for (i = 1; i < 3; i = i + 1) begin
      dflip fa (
        .din(dout[i]),
        .clk(clk),
        .res(res),
        .dout(dout[i + 1])
      );
    end
  endgenerate

endmodule

ass1/shift/TB.v
`timescale 1ns/1ns

module tbshiftreg;

    reg din;
    reg clk, res;
    wire [3:0] dout;

    // Instantiate the full adder 8-bit module
    shiftreg dut (
        .din(din),
        .clk(clk),
        .res(res),
        .dout(dout[3:0])
    );

    // Clock generation
    always #5 clk = ~clk;

    // Stimulus
    initial begin
        $dumpfile("full_adder_8bit_tb.vcd"); // Dump VCD file
        $dumpvars(0, tbshiftreg); // Dump variables

        // Reset
        res = 1;
        clk = 0;
        din = 0;
        #3;
        res = 0;
        din = 1;
        #8;

        din = 0; // Example input data
        #15;

        // More test data
        din = 1; // Example input data
        #6;

        din = 0; // Example input data
        #10;

        // Add more test data as needed

        $finish; // End simulation
    end

endmodule

ass1/shift/full_adder_8bit_tb.vcd
$date
	Fri Apr  5 12:46:38 2024
$end
$version
	Icarus Verilog
$end
$timescale
	1ns
$end
$scope module tbshiftreg $end
$var wire 4 ! dout [3:0] $end
$var reg 1 " clk $end
$var reg 1 # din $end
$var reg 1 $ res $end
$scope module dut $end
$var wire 1 " clk $end
$var wire 1 # din $end
$var wire 1 $ res $end
$var wire 4 % dout [3:0] $end
$scope begin genblk1[1] $end
$scope module fa $end
$var wire 1 " clk $end
$var wire 1 & din $end
$var wire 1 $ res $end
$var reg 1 ' dout $end
$upscope $end
$upscope $end
$scope begin genblk1[2] $end
$scope module fa $end
$var wire 1 " clk $end
$var wire 1 ( din $end
$var wire 1 $ res $end
$var reg 1 ) dout $end
$upscope $end
$upscope $end
$scope module fa $end
$var wire 1 " clk $end
$var wire 1 # din $end
$var wire 1 $ res $end
$var reg 1 * dout $end
$upscope $end
$upscope $end
$upscope $end
$enddefinitions $end
#0
$dumpvars
0*
0)
0(
0'
z&
b0z0 %
1$
0#
0"
b0z0 !
$end
#3
1#
0$
#5
1"
#10
z(
1*
b0zz1 !
b0zz1 %
z'
0"
#11
0#
#15
1"
#20
z)
bz0 !
bz0 %
0*
0"
#25
1"
#26
1#
#30
bz1 !
bz1 %
1*
0"
#32
0#
#35
1"
#40
bz0 !
bz0 %
0*
0"
